drunner.py
drunner-1.2.1.dist-info/LICENSE
drunner-1.2.1.dist-info/METADATA
drunner-1.2.1.dist-info/WHEEL
drunner-1.2.1.dist-info/entry_points.txt
drunner-1.2.1.dist-info/top_level.txt
drunner-1.2.1.dist-info/RECORD
