Metadata-Version: 2.1
Name: drunner
Version: 1.2.1
Summary: Python integration with Drunner
Home-page: UNKNOWN
Author: TimeAshore
Author-email: timeashore@163.com
License: UNKNOWN
Platform: UNKNOWN
Classifier: Operating System :: OS Independent
Classifier: Operating System :: MacOS
Classifier: Operating System :: Microsoft :: Windows
Classifier: Programming Language :: Python
Classifier: Programming Language :: Python :: 3 :: Only
Classifier: Programming Language :: Python :: 3.8
Classifier: License :: OSI Approved :: MIT License
Requires-Python: >=3.8
License-File: LICENSE
Requires-Dist: Click (>=8.1.3)
Requires-Dist: requests (>=2.27.1)
